ufma_scrapperpy/__init__.py
ufma_scrapperpy/acervobiblioteca.py
ufma_scrapperpy/curso.py
ufma_scrapperpy/docente.py
ufma_scrapperpy/subunidade.py
ufma_scrapperpy/unidade.py
ufma_scrapperpy-0.0.3.dist-info/LICENSE
ufma_scrapperpy-0.0.3.dist-info/METADATA
ufma_scrapperpy-0.0.3.dist-info/WHEEL
ufma_scrapperpy-0.0.3.dist-info/top_level.txt
ufma_scrapperpy-0.0.3.dist-info/RECORD
