Metadata-Version: 2.1
Name: ufma-scrapperpy
Version: 0.0.3
Summary: TYPE YOUR DESCRIPTION HERE
Home-page: https://github.com/inovacampus/ufma_scrapperpy
Author: Sérgio Souza Costa
Author-email: profsergiocosta@gmail.com
License: MIT
Keywords: SOME,MEANINGFULL,KEYWORDS
Platform: UNKNOWN
Classifier: Development Status :: 3 - Alpha
Classifier: Intended Audience :: Developers
Classifier: Topic :: Software Development :: Build Tools
Classifier: License :: OSI Approved :: MIT License
Classifier: Programming Language :: Python :: 3
Classifier: Programming Language :: Python :: 3.4
Classifier: Programming Language :: Python :: 3.5
Classifier: Programming Language :: Python :: 3.6
